COPYING
ChangeLog
MANIFEST.in
README
__pkginfo__.py
setup.py
bin/lgp
doc/changelog.txt
doc/index.txt
doc/makefile
doc/packaging_howto.txt
doc/pkginfo_variables.txt
doc/lgp/pristine.rst
doc/lgp/settings.rst
doc/lgp/tag.rst
etc/lgp/lgprc
etc/lgp/pbuilderrc
etc/lgp/pbuilderrc.local
etc/lgp/pbuilderrc.sh
etc/lgp/sources.list.debian
etc/lgp/sources.list.ubuntu
etc/lgp/hooks/B89diffstat
etc/lgp/hooks/B90lintian
etc/lgp/hooks/B91debc
etc/lgp/hooks/C10shell
etc/lgp/hooks/D10tmp
etc/lgp/hooks/D50debconf
etc/lgp/hooks/D99apt
etc/lgp/hooks/E00lgpmirrors
etc/lgp/hooks/E01logilab
etc/lgp/hooks/F00env
etc/lgp/hooks/F01shell
etc/lgp/hooks/F10apt
etc/lgp/hooks/F11proxy
etc/lgp/hooks/F99apt
etc/lgp/hooks/lgp.functions
etc/lgp/scripts/apt
etc/lgp/scripts/debconf
etc/lgp/scripts/debi
etc/lgp/scripts/false
etc/lgp/scripts/help
etc/lgp/scripts/install
etc/lgp/scripts/login
etc/lgp/scripts/purge
etc/lgp/scripts/pytest
etc/lgp/scripts/tracking
etc/lgp/scripts/upgrade
etc/lgp/scripts/x11shell
logilab/__init__.py
logilab/packaging/__init__.py
logilab/packaging/lgp/__init__.py
logilab/packaging/lgp/build.py
logilab/packaging/lgp/check.py
logilab/packaging/lgp/clean.py
logilab/packaging/lgp/exceptions.py
logilab/packaging/lgp/setup.py
logilab/packaging/lgp/setupinfo.py
logilab/packaging/lgp/shell.py
logilab/packaging/lgp/tag.py
logilab/packaging/lgp/utils.py
logilab/packaging/lib/__init__.py
logilab/packaging/lib/changelog.py
logilab/packaging/lib/manifest.py
logilab/packaging/lib/pkginfo.py
logilab/packaging/lib/utils.py
logilab_packaging.egg-info/PKG-INFO
logilab_packaging.egg-info/SOURCES.txt
logilab_packaging.egg-info/dependency_links.txt
logilab_packaging.egg-info/namespace_packages.txt
logilab_packaging.egg-info/requires.txt
logilab_packaging.egg-info/top_level.txt
man/lgp.1
test/unittest_architecture.py
test/unittest_build.py
test/unittest_changelog.py
test/unittest_distributions.py
test/unittest_lgputils.py
test/unittest_manifest.py
test/unittest_pkginfo.py
test/utest_utils.py
test/data/.hgignore
test/data/ChangeLog
test/data/MANIFEST.in
test/data/__init__.py
test/data/bad_file.py
test/data/bad_file.rst
test/data/bad_file.xml
test/data/good_file.py
test/data/good_file.rst
test/data/good_file.xml
test/data/warning_rest.txt
