Metadata-Version: 1.1
Name: logilab-packaging
Version: 1.3.0
Summary: tools used at Logilab to create debian packages
Home-page: http://www.logilab.org/project/logilab-packaging
Author: Logilab
Author-email: contact@logilab.fr
License: GPL
Platform: UNKNOWN
Classifier: Development Status :: 3 - Alpha
Classifier: Intended Audience :: Developers
Classifier: Topic :: Software Development :: Build Tools
Classifier: License :: OSI Approved :: GNU General Public License v2 (GPLv2)
Classifier: Programming Language :: Python :: 2
Classifier: Programming Language :: Python :: 2.6
Classifier: Programming Language :: Python :: 2.7
